Metadata-Version: 2.4
Name: patchllm
Version: 1.0.0
Summary: An interactive agent for codebase modification using LLMs
Author: nassimberrada
License: MIT License
Requires-Python: >=3.8
License-File: LICENSE
Requires-Dist: litellm
Requires-Dist: python-dotenv
Requires-Dist: rich
Requires-Dist: prompt_toolkit
Requires-Dist: InquirerPy
Provides-Extra: voice
Requires-Dist: SpeechRecognition; extra == "voice"
Requires-Dist: pyttsx3; extra == "voice"
Provides-Extra: url
Requires-Dist: html2text; extra == "url"
Provides-Extra: all
Requires-Dist: SpeechRecognition; extra == "all"
Requires-Dist: pyttsx3; extra == "all"
Requires-Dist: html2text; extra == "all"
Dynamic: license-file
